{
  "id": "spacestationv1",
  "name": "Space Station V1 for Minecraft Moon Edition",
  "author": "LCEGuys",
  "description": "a map by Shoomoo17 for Minecraft Moon Edition!",
  "extended_description": "made by shoomoo17 for Minecraft Moon Edition, made for a video coming on the LCEGuys YouTube Channel, This map was transferred from Shoomoo's Computer to Dllie's Computer using an iPod Classic, Do what you will with that information.",
  "category": [
    "World"
  ],
  "thumbnail": "InShot_20260711_195506200.jpg",
  "zips": {
    "Space Station V1 by shoomoo17.zip": "{GameHDD}"
  },
  "version": "1.0.0",
  "required_versions": [
    "moon_edition"
  ]
}
